<?xml version="1.0" encoding="UTF-8"?>
<ISUI>
  <Window name='CharacterSwap'>
    <Title>Character Swap</Title>
    <X>200</X>
    <Y>200</Y>
    <Width>1600</Width>
    <Height>30</Height>
    <Border />
    <Children>
      <frame name='main'>
        <Texture />
        <BackgroundColor />
        <Width>100%</Width>
        <Height>100%</Height>
        <Children>
          <button name='is1'>
            <X>0</X>
            <Y>0</Y>
            <Width>150</Width>
            <Height>30</Height>
            <Text>${ISBoxerSlot1}</Text>
            <OnLeftClick>
              <![CDATA[
                uplink focus is1
              ]]>
            </OnLeftClick>
          </button>
          <button name='is1_combat'>
            <X>0</X>
            <Y>30</Y>
            <Width>32</Width>
            <Height>32</Height>
            <Texture Filename='C:\Users\chris\OneDrive\Pictures 1\WoW\petbattle_attack_32x32.jpg'></Texture>
            <OnLeftClick>
              <![CDATA[
                ISBoxerUI:PopupText["Please enter a name to save the Region Set as!"]
              ]]>
            </OnLeftClick>
          </button>
          <button name='is1_follow'>
            <X>34</X>
            <Y>30</Y>
            <Width>32</Width>
            <Height>32</Height>
            <Texture Filename='C:\Users\chris\OneDrive\Pictures 1\WoW\ability_rogue_sprint_32x32.jpg'></Texture>
            <OnLeftClick>
              <![CDATA[
                ISBoxerUI:PopupText["Please enter a name to save the Region Set as!"]
              ]]>
            </OnLeftClick>
          </button>
          <button name='is1_assist'>
            <X>68</X>
            <Y>30</Y>
            <Width>32</Width>
            <Height>32</Height>
            <Texture Filename='C:\Users\chris\OneDrive\Pictures 1\WoW\ability_hunter_pet_assist_32x32.jpg'></Texture>
            <OnLeftClick>
              <![CDATA[

              ]]>
            </OnLeftClick>
          </button>

          <button name='is2'>
            <X>152</X>
            <Y>0</Y>
            <Width>150</Width>
            <Height>30</Height>
            <Text>${ISBoxerSlot2}</Text>
            <OnLeftClick>
              <![CDATA[
                uplink focus is2
              ]]>
            </OnLeftClick>
          </button>
          <button name='is2_combat'>
            <X>152</X>
            <Y>30</Y>
            <Width>32</Width>
            <Height>32</Height>
            <Texture Filename='C:\Users\chris\OneDrive\Pictures 1\WoW\petbattle_attack_32x32.jpg'></Texture>
            <OnLeftClick>
              <![CDATA[

              ]]>
            </OnLeftClick>
          </button>
          <button name='is2_follow'>
            <X>186</X>
            <Y>30</Y>
            <Width>32</Width>
            <Height>32</Height>
            <Texture Filename='C:\Users\chris\OneDrive\Pictures 1\WoW\ability_rogue_sprint_32x32.jpg'></Texture>
            <OnLeftClick>
              <![CDATA[

              ]]>
            </OnLeftClick>
          </button>
          <button name='is2_assist'>
            <X>220</X>
            <Y>30</Y>
            <Width>32</Width>
            <Height>32</Height>
            <Texture Filename='C:\Users\chris\OneDrive\Pictures 1\WoW\ability_hunter_pet_assist_32x32.jpg'></Texture>
            <OnLeftClick>
              <![CDATA[

              ]]>
            </OnLeftClick>
          </button>


          <button name='is3'>
            <X>304</X>
            <Y>0</Y>
            <Width>150</Width>
            <Height>30</Height>
            <Text>${ISBoxerSlot3}</Text>
            <OnLeftClick>
              <![CDATA[
                uplink focus is3
              ]]>
            </OnLeftClick>
          </button>
          <button name='is4'>
            <X>456</X>
            <Y>0</Y>
            <Width>150</Width>
            <Height>30</Height>
            <Text>${ISBoxerSlot4}</Text>
            <OnLeftClick>
              <![CDATA[
                uplink focus is4
              ]]>
            </OnLeftClick>
          </button>
          <button name='is5'>
            <X>608</X>
            <Y>0</Y>
            <Width>150</Width>
            <Height>30</Height>
            <Text>${ISBoxerSlot5}</Text>
            <OnLeftClick>
              <![CDATA[
                uplink focus is5
              ]]>
            </OnLeftClick>
          </button>
          <button name='is6'>
            <X>760</X>
            <Y>0</Y>
            <Width>150</Width>
            <Height>30</Height>
            <Text>${ISBoxerSlot6}</Text>
            <OnLeftClick>
              <![CDATA[
                uplink focus is6
              ]]>
            </OnLeftClick>
          </button>
          <button name='is7'>
            <X>912</X>
            <Y>0</Y>
            <Width>150</Width>
            <Height>30</Height>
            <Text>${ISBoxerSlot7}</Text>
            <OnLeftClick>
              <![CDATA[
                uplink focus is7
              ]]>
            </OnLeftClick>
          </button>
          <button name='is8'>
            <X>1064</X>
            <Y>0</Y>
            <Width>150</Width>
            <Height>30</Height>
            <Text>${ISBoxerSlot8}</Text>
            <OnLeftClick>
              <![CDATA[
                uplink focus is8
              ]]>
            </OnLeftClick>
          </button>
          <button name='is9'>
            <X>1216</X>
            <Y>0</Y>
            <Width>150</Width>
            <Height>30</Height>
            <Text>${ISBoxerSlot9}</Text>
            <OnLeftClick>
              <![CDATA[
                uplink focus is9
              ]]>
            </OnLeftClick>
          </button>
          <button name='is10'>
            <X>1368</X>
            <Y>0</Y>
            <Width>150</Width>
            <Height>30</Height>
            <Text>${ISBoxerSlot10}</Text>
            <OnLeftClick>
              <![CDATA[
                uplink focus is10
              ]]>
            </OnLeftClick>
          </button>
        </Children>
      </frame>
    </Children>
  </Window>
</ISUI>
